easy_logging/__init__.py
easy_logging/config.py
easy_logging/formatter.py
easy_logging/styling.py
easy_logging_formatter-0.1.1.dist-info/licenses/LICENSE
easy_logging_formatter-0.1.1.dist-info/METADATA
easy_logging_formatter-0.1.1.dist-info/WHEEL
easy_logging_formatter-0.1.1.dist-info/top_level.txt
easy_logging_formatter-0.1.1.dist-info/RECORD
