Metadata-Version: 2.4
Name: easy-logging-formatter
Version: 0.1.1
Summary: An easy, customizable formatter for Python logging
Author: Jatewo
License: GNU GENERAL PUBLIC LICENSE
Project-URL: Homepage, https://github.com/Jatewo/easy-logging
Project-URL: Issues, https://github.com/Jatewo/easy-logging/issues
Keywords: logging,formatter,json,colors,logger,dev-tools
Classifier: Development Status :: 4 - Beta
Classifier: Intended Audience :: Developers
Classifier: Topic :: System :: Logging
Classifier: Topic :: Software Development :: Libraries :: Python Modules
Classifier: Operating System :: OS Independent
Classifier: Programming Language :: Python :: 3
Classifier: Programming Language :: Python :: 3.12
Classifier: License :: OSI Approved :: GNU General Public License v3 (GPLv3)
Requires-Python: >=3.12
License-File: LICENSE
Dynamic: license-file
